plain/pytest/CHANGELOG.md
plain/pytest/README.md
plain/pytest/__init__.py
plain/pytest/browser.py
plain/pytest/cli.py
plain/pytest/entrypoints.py
plain/pytest/plugin.py
plain/pytest/skills/plain-test/SKILL.md
plain_pytest-0.16.0.dist-info/METADATA
plain_pytest-0.16.0.dist-info/WHEEL
plain_pytest-0.16.0.dist-info/entry_points.txt
plain_pytest-0.16.0.dist-info/licenses/LICENSE
plain_pytest-0.16.0.dist-info/RECORD
