Metadata-Version: 2.4
Name: plain.pytest
Version: 0.16.0
Summary: Test with pytest.
Author-email: Dave Gaeddert <dave.gaeddert@dropseed.dev>
License-Expression: BSD-3-Clause
License-File: LICENSE
Requires-Python: >=3.13
Requires-Dist: click>=8.0.0
Requires-Dist: cryptography
Requires-Dist: plain<1.0.0
Requires-Dist: pytest>=7.0.0
